Workbook

Sheet Dashboard
C3: Solar panels
F4: FY24 | G4: FY25E | H4: FY26E | I4: FY27E
B5: Roll No. | C5: Name | E5: Expansion (Cities And Segment | F5: Bhopal | G5: Bhopal, Jaipur, Chandigarh and Lucknow | H5: Bhopal, Jaipur, Chandigarh, Noida, Gurugram and Lucknow Include commercial Buildings | I5: Bhopal, Jaipur, Chandigarh, Noida, Gurugram, dehradun, Jodhpur, Amritsar, Ludhiana and Lucknow Include commercial Buildings
B6: I002 | C6: Utkarsh Bhattar
B7: I015 | C7: Kedar Lad
B8: I026 | C8: Arjun Saxena
B9: I030 | C9: Aman Sharma | E9: Number of cities | F9: 1 | G9: 4 | H9: 6+ | I9: 10+
B10: I038 | C10: Aditya Trivedi
B11: I076 | C11: Aditi Garje

Sheet Cost Structure
A1: CAPITAL COST FOR ROOF TOP SOLAR PLANT
A3: Capital cost of 5 Kilowatt capacity Roof Top Solar Plant | C3: 5 | D3: FY24 | E3: FY25E | F3: FY26E | G3: FY27E
A5: S.No. | B5: Equipment/ Material | C5: Unit | D5: Cost in INR (for 5 kW)
B6: Selling Price | D6: 275000 | E6: 300000 | F6: ='Assets, Net Revenue Projections'!F30 -> 319000 | G6: 339375
A8: 1 | B8: Solar PV modules | C8: Watt | D8: 80000 | E8: 84000 | F8: 88000 | G8: 92000
A10: 2 | B10: Solar Panel mounting Structure | C10: kW | D10: 17500 | E10: 18000 | F10: 18500 | G10: 19000
A12: 3 | B12: Inverter | C12: kW | D12: 15000 | E12: 16000 | F12: 17000 | G12: 18000
A14: 4 | B14: DC cables, AC cables, Meter and other Miscellaneous items | C14: kW | D14: 10000 | E14: 10250 | F14: 10500 | G14: 10800
A16: 5 | B16: Contingency Cost | C16: kW | D16: 10000 | E16: 12000 | F16: 13000 | G16: 14000
B18: Sub Total (1+2+3+4) | D18: =D8+D10+D12+D14+D16 -> 132500 | E18: =E8+E10+E12+E14+E16 -> 140250 | F18: =F8+F10+F12+F14+F16 -> 147000 | G18: =G8+G10+G12+G14+G16 -> 153800
A20: 6 | B20: Installation Cost (7% of revenue) | D20: =0.07*D6 -> 19250 | E20: =0.07*E6 -> 21000 | F20: =0.07*F6 -> 22330 | G20: =0.07*G6 -> 23756.25
A22: 7 | B22: GST @ 12% on Selling Price charged to client, inluded in MRP) | D22: =0.12*D6 -> 33000 | E22: =0.12*E6 -> 36000 | F22: =0.12*F6 -> 38280 | G22: =0.12*G6 -> 40725
A24: 8 | B24: Total Cost (Sub Total +GST+Installation Cost) | D24: =D18+D22+D20 -> 184750 | E24: =E18+E22+E20 -> 197250 | F24: =F18+F22+F20 -> 207610 | G24: =G18+G22+G20 -> 218281.25
A26: 9 | B26: Gross Profit on installation (Selling Price- Total Cost) | D26: =D6-D24 -> 90250 | E26: =E6-E24 -> 102750 | F26: =F6-F24 -> 111390 | G26: =G6-G24 -> 121093.75
A28: 10 | B28: Change in Cost percentge from previous year (Selling Price) | E28: =(E6-D6)/D6 -> 0.090909091 | F28: =(F6-E6)/E6 -> 0.063333333 | G28: =(G6-F6)/F6 -> 0.063871473
A30: 11 | B30: Gross Margins for installation | D30: =D26/D6 -> 0.32818182 | E30: =E26/E6 -> 0.3425 | F30: =F26/F6 -> 0.34918495 | G30: =G26/G6 -> 0.356814
A32: 12 | B32: Change in Cost percentge from previous year (Cost Price) | E32: =(E24-D24)/D24 -> 0.067658999 | F32: =(F24-E24)/E24 -> 0.05252218 | G32: =(G24-F24)/F24 -> 0.051400462

Sheet Balance Sheet
C2: Balance Sheet
E3: as on 31st March 2024
B4: S.No. | C4: Particulars | D4: Note No. | E4: FY24
C5: Assets
B6: 1 | C6: Non-Current Assets
C7: Property, plant and equipments | E7: 900000
C8: Total Non-Current Assets | E8: =E7 -> 900000
B10: 2 | C10: Current Assets
C11: Inventories | E11: 2120000
C12: Trade Receivables | E12: 4400000
C13: Cash And Cash equivalents | E13: 1046000
C14: Bank Balance Other than cash and cash equivelents | E14: 3800000
C15: Total Current Assets | E15: 11366000
C17: Total Assets | E17: =SUM(E8,E15) -> 12266000
C19: Equity and Liabilities
C20: Equity
C21: Equity Share Capital | E21: 4000000
C22: Retained Earnings | E22: 5616000
C23: Total Equity | E23: 9616000
B24: 1
C25: Liabilities
C26: Non-Current Liabilities
C27: Financial Liabilities
C28: Borrowings | E28: 0
C29: Total Non-Current Liabilities | E29: 0
C32: Current Liabilities
C33: Financial Liabilities
C34: Borrowings | E34: 0
C35: Trade Payables | E35: 2650000
C36: Total Current Liabilities | E36: 2650000
C38: Total Equity and Liabilities | E38: =SUM(E36,E23) -> 12266000

Sheet Income Sheet FY24E
C2: Income Sheet FY24E
B5: S No. | C5: Particulars | D5: FY24
B6: 1 | C6: Income
C7: a) Revenue from Operations | D7: 28600000
C8: b) Other Income
C9: Total Income | D9: 28600000
B11: 2 | C11: COGS
C12: Purchase of Stock-in-Trade | D12: 15900000
C13: Charge in inventories of Finished Goods, | D13: 2120000
C14: Payment of GST | D14: 3432000
C15: EBITDA | D15: 11388000
C17: Employee Benefits Expense | D17: 3500000
C18: Other Costs | D18: 1000000
C19: Depreciation and Amortization Expense | D19: 100000
C22: Profit Before tax and Interest | D22: 6788000
C24: Interest | D24: 0
C26: Profit Before tax | D26: 6788000
C28: Tax Expense
C29: Corporate Tax | D29: 1697000
C31: Profit for the year | D31: 5091000
C33: Dividends | D33: 1000000
C35: Retained earnings | D35: 4091000

Sheet Income Statement
B2: Income Statement
D3: for the year 2024
B4: S No. | C4: Particulars | D4: FY24 | E4: FY25E | F4: FY26E | G4: FY27E
B5: 1 | C5: Income
C6: a) Revenue from Operations | D6: ='Projected Costs'!B6*'Projected Costs'!B9 -> 28600000 | E6: ='Projected Costs'!C6*'Projected Costs'!C9 -> 75000000 | F6: ='Projected Costs'!D6*'Projected Costs'!D9 -> 239250000 | G6: ='Projected Costs'!E6*'Projected Costs'!E9 -> 543000000
C7: b) Other Income
C8: Total Income | D8: =D6 -> 28600000 | E8: =E6 -> 75000000 | F8: =F6 -> 239250000 | G8: =G6 -> 543000000
B10: 2 | C10: COGS
C11: Purchase of Stock-in-Trade | D11: ='Projected Costs'!B5*'Projected Costs'!B8 -> 15900000 | E11: ='Projected Costs'!C5*'Projected Costs'!C8 -> 36465000 | F11: ='Projected Costs'!D5*'Projected Costs'!D8 -> 114660000 | G11: ='Projected Costs'!E5*'Projected Costs'!E8 -> 249156000
C12: Charge in inventories of Finished Goods, | D12: ='Projected Costs'!B5*('Projected Costs'!B8-'Projected Costs'!B9) -> 2120000 | E12: ='Projected Costs'!C5*('Projected Costs'!C8-'Projected Costs'!C9) -> 1402500 | F12: ='Projected Costs'!D5*('Projected Costs'!D8-'Projected Costs'!D9) -> 4410000 | G12: ='Projected Costs'!E5*('Projected Costs'!E8-'Projected Costs'!E9) -> 3076000
C13: Payment of GST | D13: ='Income Statement'!D6*0.12 -> 3432000 | E13: ='Income Statement'!E6*0.12 -> 9000000 | F13: ='Income Statement'!F6*0.12 -> 28710000 | G13: ='Income Statement'!G6*0.12 -> 65160000
C14: EBITDA | D14: =D8-D11+D12-D13 -> 11388000 | E14: =E8-E11+E12-E13 -> 30937500 | F14: =F8-F11+F12-F13 -> 100290000 | G14: =G8-G11+G12-G13 -> 231760000
C16: Employee Benefits Expense | D16: ='Projected Costs'!B10*'Projected Costs'!B11 -> 3500000 | E16: ='Projected Costs'!C10*'Projected Costs'!C11 -> 15000000 | F16: ='Projected Costs'!D10*'Projected Costs'!D11 -> 36000000 | G16: ='Projected Costs'!E10*'Projected Costs'!E11 -> 72000000
C17: Other Costs | D17: ='Assets, Net Revenue Projections'!C16 -> 1000000 | E17: ='Assets, Net Revenue Projections'!D16 -> 4600000 | F17: ='Assets, Net Revenue Projections'!E16 -> 11200000 | G17: ='Assets, Net Revenue Projections'!F16 -> 22700000
C18: Depreciation and Amortization Expense | D18: ='Assets, Net Revenue Projections'!C6 -> 100000 | E18: ='Assets, Net Revenue Projections'!D6 -> 990000 | F18: ='Assets, Net Revenue Projections'!E6 -> 2691000 | G18: ='Assets, Net Revenue Projections'!F6 -> 4421900
C21: Profit Before tax and Interest | D21: =D14-SUM(D16:D18) -> 6788000 | E21: =E14-SUM(E16:E19) -> 10347500 | F21: =F14-SUM(F16:F18) -> 50399000 | G21: =G14-SUM(G16:G18) -> 132638100
C23: Interest | D23: 0 | E23: ='Payment Schedule'!D6 -> 3340997.9 | F23: ='Payment Schedule'!D8 -> 2209052.5 | G23: ='Payment Schedule'!D10 -> 842283.99
C25: Profit Before tax | D25: =D21 -> 6788000 | E25: =E21 -> 10347500 | F25: =F21 -> 50399000 | G25: =G21 -> 132638100
C27: Tax Expense
C28: Corporate Tax | D28: =D25*0.25 -> 1697000 | E28: =E25*0.25 -> 2586875 | F28: =F25*0.25 -> 12599750 | G28: =G25*0.25 -> 33159525
C30: Profit for the year | D30: =D25-D28 -> 5091000 | E30: =E25-E28 -> 7760625 | F30: =F25-F28 -> 37799250 | G30: =G25-G28 -> 99478575
C32: Dividends | D32: 0 | E32: 1500000 | F32: 2000000 | G32: 2500000
C34: Retained earnings | D34: =D30-D32 -> 5091000 | E34: =E30-E32 -> 6260625 | F34: =F30-F32 -> 35799250 | G34: =G30-G32 -> 96978575
C36: CFAT | D36: =D30+D18 -> 5191000 | E36: =E30+E18 -> 8750625 | F36: =F30+F18 -> 40490250 | G36: =G30+G18 -> 103900475
C38: No. of Shares | D38: 10000000 | E38: 10000000 | F38: 10000000 | G38: 10000000
C40: Earnings Per Share | D40: =D30/D38 -> 0.5091 | E40: =E30/E38 -> 0.7760625 | F40: =F30/F38 -> 3.779925 | G40: =G30/G38 -> 9.9478575
C42: Dividends per share | D42: =D32/D38 -> 0 | E42: =E32/E38 -> 0.15 | F42: =F32/F38 -> 0.2 | G42: =G32/G38 -> 0.25

Sheet Projected Costs
A2: Projected Growth
B3: FY24 | C3: FY25E | D3: FY26E | E3: FY27E | G3: 1 Unit = | H3: 5Kw
A4: Unit Installed | B4: 104 | C4: 250 | D4: 750 | E4: 1600
A5: Cost per unit | B5: ='Cost Structure'!D18 -> 132500 | C5: ='Cost Structure'!E18 -> 140250 | D5: ='Cost Structure'!F18 -> 147000 | E5: ='Cost Structure'!G18 -> 153800
A6: Selling Price per unit | B6: ='Cost Structure'!D6 -> 275000 | C6: ='Cost Structure'!E6 -> 300000 | D6: ='Cost Structure'!F6 -> 319000 | E6: ='Cost Structure'!G6 -> 339375
A7: Revenue
A8: Inventory Bought | B8: 120 | C8: 260 | D8: 780 | E8: 1620
A9: Inventroy Sold | B9: 104 | C9: 250 | D9: 750 | E9: 1600
A10: Average EBS | B10: 700000 | C10: 750000 | D10: 800000 | E10: 900000
A11: Employees | B11: 5 | C11: 20 | D11: 45 | E11: 80
A12: No. of Ofiices | B12: 1 | C12: 4 | D12: 6 | E12: 10
A13: Expense per office and warehouse | B13: 1000000 | C13: 900000 | D13: 1100000 | E13: 1150000

Sheet Projected CFAT
A1: Projected CFAT
B2: FY25E | C2: FY26E | D2: FY27E
A3: Net Income | B3: ='Income Statement'!E30 -> 7760625 | C3: ='Income Statement'!F30 -> 37799250 | D3: ='Income Statement'!G30 -> 99478575
A4: Deprecitation | B4: ='Income Statement'!E18 -> 990000 | C4: ='Income Statement'!F18 -> 2691000 | D4: ='Income Statement'!G18 -> 4421900
A6: CFAT | B6: =SUM(B3:B4) -> 8750625 | C6: =SUM(C3:C4) -> 40490250 | D6: =SUM(D3:D4) -> 103900475

Sheet Assets, Net Revenue Projections
B1: Assets
C3: 2023-24 FY | D3: 2024-25 FY | E3: 2025-26 FY | F3: 2026-27 FY
B4: Net Asset at starting | C4: 0 | D4: =C7 -> 900000 | E4: =D7 -> 8910000 | F4: =E7 -> 24219000
B5: New Purchase | C5: 1000000 | D5: 9000000 | E5: 18000000 | F5: 20000000
B6: Deprectiation | C6: =0.1*C5 -> 100000 | D6: =0.1*(D5+D4) -> 990000 | E6: =0.1*(E5+E4) -> 2691000 | F6: =0.1*(F5+F4) -> 4421900
B7: Net Asset at Ending | C7: =C5-C6 -> 900000 | D7: =D4+D5-D6 -> 8910000 | E7: =E4+E5-E6 -> 24219000 | F7: =F4+F5-F6 -> 39797100
B11: Other Cost
C13: 2023-24 FY | D13: 2024-25 FY | E13: 2025-26 FY | F13: 2026-27 FY
B14: Net Rent at starting | C14: 0 | D14: =C16 -> 1000000 | E14: =D16 -> 4600000 | F14: =E16 -> 11200000
B15: New Rent Expense | C15: ='Projected Costs'!B12*'Projected Costs'!B13 -> 1000000 | D15: ='Projected Costs'!C12*'Projected Costs'!C13 -> 3600000 | E15: ='Projected Costs'!D12*'Projected Costs'!D13 -> 6600000 | F15: ='Projected Costs'!E12*'Projected Costs'!E13 -> 11500000
B16: Net Rent at Ending | C16: =SUM(C14:C15) -> 1000000 | D16: =SUM(D14:D15) -> 4600000 | E16: =SUM(E14:E15) -> 11200000 | F16: =SUM(F14:F15) -> 22700000
B20: Net Revenue Projections
B22: FY24 | D22: FY25E | F22: FY26E | H22: FY27E
B23: B2C | C23: B2B | D23: B2C | E23: B2B | F23: B2C | G23: B2B | H23: B2C | I23: B2B
A24: Units | B24: ='Projected Costs'!B4 -> 104 | C24: 0 | D24: 250 | F24: 600 | G24: 15 | H24: 1000 | I24: 60
A25: break up units | B25: =B24*5 -> 520 | C25: =B26-B25 -> 0 | D25: =D24*5 -> 1250 | F25: =F24*5 -> 3000 | G25: =F26-F25 -> 750 | H25: =H24*5 -> 5000 | I25: =H26-H25 -> 3000
A26: Total Units | B26: =B24*5+C24*50 -> 520 | D26: =D24*5+E24*50 -> 1250 | F26: =F24*5+G24*50 -> 3750 | H26: =H24*5+I24*50 -> 8000
A27: Average cost price | B27: ='Projected Costs'!B6 -> 275000 | D27: 300000 | F27: 320000 | G27: 3150000 | H27: 345000 | I27: 3300000
A28: Revenue Projected | B28: =B24*B27 -> 28600000 | C28: =C24*C27 -> 0 | D28: =D24*D27 -> 75000000 | E28: =E24*E27 -> 0 | F28: =F24*F27 -> 192000000 | G28: =G24*G27 -> 47250000 | H28: =H24*H27 -> 345000000 | I28: =I24*I27 -> 198000000
A29: Total Revenue Projected | B29: =B28+C28 -> 28600000 | D29: =D28+E28 -> 75000000 | F29: =F28+G28 -> 239250000 | H29: =H28+I28 -> 543000000
A30: Cost per 5kW | B30: =B29/B26*5 -> 275000 | D30: =D29/D26*5 -> 300000 | F30: =F29/F26*5 -> 319000 | H30: =H29/H26*5 -> 339375
A31: % Break up | B31: =B25/B26 -> 1 | C31: =C25/B26 -> 0 | D31: =D25/D26 -> 1 | E31: =E25/D26 -> 0 | F31: =F25/F26 -> 0.8 | G31: =G25/F26 -> 0.2 | H31: =H25/H26 -> 0.625 | I31: =I25/H26 -> 0.375
B32: Every B2C unit | C32: 5kW
B33: Every B2B unit | C33: 50kW

Sheet Payment Schedule
C2: Payment Schedule
B5: Year | C5: Principal (A) | D5: Interest (B) | E5: Total Payment (A + B) | F5: Balance | G5: Loan Paid To Date
B6: 2025 | C6: 5456446.9 | D6: 3340997.9 | E6: 8797444.8 | F6: 14543553 | G6: 0.2728
B8: 2026 | C8: 6588392.3 | D8: 2209052.5 | E8: 8797444.8 | F8: 7955160.8 | G8: 0.6022
B10: 2027 | C10: 7955160.8 | D10: 842283.99 | E10: 8797444.8 | F10: 0 | G10: 1
B12: Sum | C12: =SUM(C10+C8+C6) -> 20000000 | D12: =SUM(D10+D8+D6) -> 6392334.4

Sheet Capital Budgeting
A1: Capital Budgeting
A2: NPV | B2: NPV = [cash flow / (1+i)^t] - initial investment
D3: FY25E | E3: FY26E | F3: FY27E
B4: Inflow | D4: ='Projected CFAT'!B6 -> 8750625 | E4: ='Projected CFAT'!C6 -> 40490250 | F4: ='Projected CFAT'!D6 -> 103900475
B6: Outflow | D6: 30000000
B8: Cost of Capital | D8: ='Cost of Capital'!G40 -> 0.27249544 | E8: ='Cost of Capital'!G40 -> 0.27249544 | F8: 0.2725
B10: NPV (Inflow) | D10: =D4/(1+D8)^1 -> 6876743.7 | E10: =E4/(1+E8)^2 -> 25005641 | F10: =F4/(1+F8)^3 -> 50424797
B12: NPV (Outflow) | C12: 30000000
B15: NPV | C15: =SUM(D10:F10)-C12 -> 52307182
B17: IRR | C17: 90.604 | G17: percent
B19: PI | C19: =SUM(D10:F10)/C12 -> 2.7435727 | G19: times

Sheet Cost of Capital
A1: Cost of Capital
A3: Kd | B3: I(1-t)+(RV-NP)/Nm
B4: (RV+NP)/2
C7: Interest | D7: ='Payment Schedule'!D12 -> 6392334.4
C8: Tax Rate | D8: 0.25
C9: Redeemable value | D9: ='Payment Schedule'!C12 -> 20000000
C10: Net Proceeds | D10: =D9 -> 20000000
C11: Maturity Period | D11: 3
B14: Kd
C16: Num | D16: =D7*(1-D8) -> 4794250.8
C17: Den | D17: =(D9+D10)/2 -> 20000000
B19: Kd | D19: =D16/D17 -> 0.23971254
C21: No. of Shares declared | D21: 10000000
C22: Equity offered | D22: 0.1
C24: Proceeds | D24: 10000000
C25: Floatation Cost | D25: 200000
B26: Ke | C26: Net Proceeds | D26: =D24-D25 -> 9800000
C27: Dividends | D27: 1500000
C28: g | D28: =0.185 -> 0.185 | F28: 1= | G28: 0.1(1+x)^3
C29: No. of Shares | D29: 10000000
C30: Net Proceeds/ share | D30: =D26/D29 -> 0.98
C31: Dividends/share | D31: =D27/D29 -> 0.15
B33: Ke | D33: =(D31/D30)+D28 -> 0.33806122
C36: Source | D36: Amt | E36: wt | F36: K | G36: wt*k
C37: Debt | D37: 20000000 | E37: =D37/D39 -> 0.66666667 | F37: =D19 -> 0.23971254 | G37: =F37*E37 -> 0.15980836
C38: Equity | D38: 10000000 | E38: =D38/D39 -> 0.33333333 | F38: =D33 -> 0.33806122 | G38: =F38*E38 -> 0.11268707
D39: =D37+D38 -> 30000000
F40: WACC | G40: =G37+G38 -> 0.27249544

Sheet Leverage
A1: Leverage
B2: DFL | C2: EBIT/EBIT – I –Dp / ( 1-t)
B3: DOL | C3: Sales-Variable cost/EBIT
B4: DCL | C4: DOL X DFL
B8: S No. | C8: Particulars | D8: FY24 | E8: FY25E | F8: FY26E | G8: FY27E
B9: 1 | C9: Income
C10: a) Revenue from Operations | D10: 28600000 | E10: 75000000 | F10: 239250000 | G10: 543000000
C11: b) Other Income
C12: Total Income | D12: 28600000 | E12: 75000000 | F12: 239250000 | G12: 543000000
B14: 2 | C14: COGS
C15: Purchase of Stock-in-Trade | D15: 15900000 | E15: 36465000 | F15: 114660000 | G15: 249156000
C16: Charge in inventories of Finished Goods, | D16: 2120000 | E16: 1402500 | F16: 4410000 | G16: 3076000
C17: Payment of GST | D17: 3432000 | E17: 9000000 | F17: 28710000 | G17: 65160000
C18: EBITDA | D18: 11388000 | E18: 30937500 | F18: 100290000 | G18: 231760000
C20: Employee Benefits Expense | D20: 3500000 | E20: 15000000 | F20: 36000000 | G20: 72000000
C21: Other Costs | D21: 1000000 | E21: 4600000 | F21: 11200000 | G21: 22700000
C22: Depreciation and Amortization Expense | D22: 100000 | E22: 990000 | F22: 2691000 | G22: 4421900
C25: Profit Before tax and Interest | D25: 6788000 | E25: 10347500 | F25: 50399000 | G25: 132638100
C27: Interest | D27: 0 | E27: 3340997.9 | F27: 2209052.5 | G27: 842283.99
C29: Profit Before tax | D29: 6788000 | E29: 10347500 | F29: 50399000 | G29: 132638100
C31: Tax Expense
C32: Corporate Tax | D32: 1697000 | E32: 2586875 | F32: 12599750 | G32: 33159525
C34: Profit for the year | D34: 5091000 | E34: 7760625 | F34: 37799250 | G34: 99478575
C36: CFAT | D36: 5191000 | E36: 8900625 | F36: 43445250 | G36: 110942975
B38: DFL | C38: EBIT | D38: =D25 -> 6788000 | E38: =E25 -> 10347500 | F38: =F25 -> 50399000 | G38: =G25 -> 132638100
C39: EBIT-I-Dp/(1-t) | D39: =D25-D27 -> 6788000 | E39: =E25-E27 -> 7006502.1 | F39: =F25-F27 -> 48189947 | G39: =G25-G27 -> 1.3179582e+08 | H39: *Preference Dividend is ZERO
C41: Variable cost | D41: =D15-D16 -> 13780000 | E41: =E15-E16 -> 35062500 | F41: =F15-F16 -> 110250000 | G41: =G15-G16 -> 246080000
B43: DOL | C43: Sales-Variable cost | D43: =D41 -> 13780000 | E43: =E41 -> 35062500 | F43: =F41 -> 110250000 | G43: =G41 -> 246080000
C44: EBIT | D44: =D25 -> 6788000 | E44: =E25 -> 10347500 | F44: =F25 -> 50399000 | G44: =G25 -> 132638100
C46: DFL | D46: =D38/D39 -> 1 | E46: =E38/E39 -> 1.4768425 | F46: =F38/F39 -> 1.0458405 | G46: =G38/G39 -> 1.0063908 | H46: times
C47: DOL | D47: =D43/D44 -> 2.030053 | E47: =E43/E44 -> 3.3884996 | F47: =F43/F44 -> 2.1875434 | G47: =G43/G44 -> 1.8552739 | H47: times
C48: DCL | D48: =D46*D47 -> 2.030053 | E48: =E46*E47 -> 5.0042802 | F48: =F46*F47 -> 2.2878215 | G48: =G46*G47 -> 1.8671306 | H48: times
